{
  "meta": {
    "schema_version": 4,
    "id": "g0d_of_heads",
    "name": "G0d of Heads",
    "version": "2.0.0",
    "link": "https://github.com/Passion-Never-Dissipate/G0d-of-Heads",
    "authors": [
      "SeeU_SAMA,FRUITS_CANDY"
    ],
    "dependencies": {
      "mcdreforged": ">=2.6.0"
    },
    "requirements": [],
    "description": {
      "en_us": "获取任意玩家的任意数量的头颅，适配全版本"
    }
  },
  "plugin": {
    "schema_version": 1,
    "id": "g0d_of_heads",
    "authors": [
      "FRUITS_CANDY",
      "Seeu_SAMA"
    ],
    "repository": "https://github.com/Passion-Never-Dissipate/G0d-of-Heads",
    "branch": "master",
    "related_path": ".",
    "labels": [
      "tool"
    ],
    "introduction": {
      "zh_cn": "# GOD OF HEADS\n---------\n一个简单的获取任意数量玩家头颅的插件。\n\n重要更新，请下载最新版。\n\nv2.0.0更改日志：\n\n1，修复了1.20.5-1.20.6因为从NBT更新到物品堆叠组件导致无法使用插件的问题。\n\n2，更改了部分文本描述。\n\n3，重构了主要代码。\n\n需要 `v2.6.0` 以上的 [MCDReforged](https://github.com/Fallen-Breath/MCDReforged)\n\n## 命令基本说明\n\n`!!head <玩家X名称> [数量Y]` 获取玩家X的头颅Y个，当Y未指定时，默认为1。\n\n建议获取数量不要超过一组。\n\n[PND](https://github.com/orgs/Passion-Never-Dissipate/repositories)原版技术生存群组服\n\nQQ交流群：417086159\n\n\n\n\n\n\n\n\n"
    },
    "introduction_urls": {
      "zh_cn": "https://raw.githubusercontent.com/Passion-Never-Dissipate/G0d-of-Heads/master/README.md"
    }
  },
  "release": {
    "schema_version": 8,
    "id": "g0d_of_heads",
    "latest_version": "2.0.0",
    "latest_version_index": 0,
    "releases": [
      {
        "url": "https://github.com/Passion-Never-Dissipate/G0d-of-Heads/releases/tag/2.0.0",
        "name": "G0d-of-Heads-v2.0.0",
        "tag_name": "2.0.0",
        "created_at": "2025-02-23T03:00:03Z",
        "description": "重要更新，请下载最新版。\r\n更改日志：\r\n    1，修复了1.20.5-1.20.6因为从NBT更新到物品堆叠组件导致无法使用插件的问题。\r\n    2，更改了部分文本描述。\r\n    3，重构了主要代码。",
        "prerelease": false,
        "asset": {
          "id": 235750649,
          "name": "G0d-of-Heads-v2.0.0.mcdr",
          "size": 16192,
          "download_count": 355,
          "created_at": "2025-03-08T17:34:44Z",
          "browser_download_url": "https://github.com/Passion-Never-Dissipate/G0d-of-Heads/releases/download/2.0.0/G0d-of-Heads-v2.0.0.mcdr",
          "hash_md5": "668742ef1feb779724e2b641a0792aa9",
          "hash_sha256": "797df9f24650a78858c8167d9c163c717430b76a9ded80a4f7a78a7743f1df5f"
        },
        "meta": {
          "schema_version": 4,
          "id": "g0d_of_heads",
          "name": "G0d of Heads",
          "version": "2.0.0",
          "link": "https://github.com/Passion-Never-Dissipate/G0d-of-Heads",
          "authors": [
            "SeeU_SAMA,FRUITS_CANDY"
          ],
          "dependencies": {
            "mcdreforged": ">=2.6.0"
          },
          "requirements": [
            "mcdreforged>=2.6.0"
          ],
          "description": {
            "en_us": "获取任意玩家的任意数量的头颅，适配全版本"
          }
        }
      },
      {
        "url": "https://github.com/Passion-Never-Dissipate/G0d-of-Heads/releases/tag/1.1.0",
        "name": "G0d-of-Heads-v1.1.0",
        "tag_name": "1.1.0",
        "created_at": "2025-02-18T04:10:40Z",
        "description": "对1.21+版本进行了适配",
        "prerelease": false,
        "asset": {
          "id": 230117380,
          "name": "G0d-of-Heads-v1.1.0.mcdr",
          "size": 13638,
          "download_count": 78,
          "created_at": "2025-02-18T04:12:31Z",
          "browser_download_url": "https://github.com/Passion-Never-Dissipate/G0d-of-Heads/releases/download/1.1.0/G0d-of-Heads-v1.1.0.mcdr",
          "hash_md5": "dec8d0b13d3fc13f69ff75f9e214bcd5",
          "hash_sha256": "cc3372cb98f123cc7ff715ff9444b203e7c5c441b2b131c97c3f9a1510390657"
        },
        "meta": {
          "schema_version": 4,
          "id": "g0d_of_heads",
          "name": "G0d of Heads",
          "version": "1.1.0",
          "link": "https://github.com/Passion-Never-Dissipate/G0d-of-Heads",
          "authors": [
            "SeeU_SAMA,FRUITS_CANDY"
          ],
          "dependencies": {
            "mcdreforged": ">=2.6.0"
          },
          "requirements": [
            "mcdreforged>=2.6.0"
          ],
          "description": {
            "en_us": "获取任意玩家的任意数量的头颅"
          }
        }
      },
      {
        "url": "https://github.com/Passion-Never-Dissipate/G0d-of-Heads/releases/tag/1.0.0",
        "name": "G0d-of-Heads-v1.0.0",
        "tag_name": "1.0.0",
        "created_at": "2025-01-31T11:57:04Z",
        "description": "第一个release，后续会继续更新",
        "prerelease": false,
        "asset": {
          "id": 225165118,
          "name": "G0d-of-Heads-v1.0.0.mcdr",
          "size": 13600,
          "download_count": 77,
          "created_at": "2025-01-31T13:36:15Z",
          "browser_download_url": "https://github.com/Passion-Never-Dissipate/G0d-of-Heads/releases/download/1.0.0/G0d-of-Heads-v1.0.0.mcdr",
          "hash_md5": "05fad34424418f0203d674409fa82bf2",
          "hash_sha256": "0fdf848713416ae40ae8d5db39dc21113cc4bd83e1aab55c4b25188d28669d35"
        },
        "meta": {
          "schema_version": 4,
          "id": "g0d_of_heads",
          "name": "G0d of Heads",
          "version": "1.0.0",
          "link": "https://github.com/Passion-Never-Dissipate/G0d-of-Heads",
          "authors": [
            "SeeU_SAMA,FRUITS_CANDY"
          ],
          "dependencies": {
            "mcdreforged": ">=2.6.0"
          },
          "requirements": [
            "mcdreforged>=2.6.0"
          ],
          "description": {
            "en_us": "获取任意玩家的任意数量的头颅"
          }
        }
      }
    ]
  },
  "repository": {
    "url": "https://github.com/Passion-Never-Dissipate/G0d-of-Heads",
    "name": "G0d-of-Heads",
    "full_name": "Passion-Never-Dissipate/G0d-of-Heads",
    "html_url": "https://github.com/Passion-Never-Dissipate/G0d-of-Heads",
    "description": "一个简单的获取任意数量玩家头颅的插件。",
    "archived": false,
    "stargazers_count": 0,
    "watchers_count": 0,
    "forks_count": 1,
    "readme": "# GOD OF HEADS\n---------\n一个简单的获取任意数量玩家头颅的插件。\n\n重要更新，请下载最新版。\n\nv2.0.0更改日志：\n\n1，修复了1.20.5-1.20.6因为从NBT更新到物品堆叠组件导致无法使用插件的问题。\n\n2，更改了部分文本描述。\n\n3，重构了主要代码。\n\n需要 `v2.6.0` 以上的 [MCDReforged](https://github.com/Fallen-Breath/MCDReforged)\n\n## 命令基本说明\n\n`!!head <玩家X名称> [数量Y]` 获取玩家X的头颅Y个，当Y未指定时，默认为1。\n\n建议获取数量不要超过一组。\n\n[PND](https://github.com/orgs/Passion-Never-Dissipate/repositories)原版技术生存群组服\n\nQQ交流群：417086159\n\n\n\n\n\n\n\n\n",
    "readme_url": "https://raw.githubusercontent.com/Passion-Never-Dissipate/G0d-of-Heads/master/README.md",
    "license": {
      "key": "gpl-3.0",
      "name": "GNU General Public License v3.0",
      "spdx_id": "GPL-3.0",
      "url": "https://api.github.com/licenses/gpl-3.0"
    }
  }
}