{
  "url": "https://github.com/Mooling0602/Ender-Pearl-TP-MCDR",
  "name": "Ender-Pearl-TP-MCDR",
  "full_name": "Mooling0602/Ender-Pearl-TP-MCDR",
  "html_url": "https://github.com/Mooling0602/Ender-Pearl-TP-MCDR",
  "description": null,
  "archived": false,
  "stargazers_count": 0,
  "watchers_count": 0,
  "forks_count": 0,
  "readme": "- [中文](https://github.com/Mooling0602/Ender-Pearl-TP-MCDR/blob/main/README_zh_cn.md)\n\n# Ender Pearl TP-MCDR\nCost some ender pearls to teleport to anywhere, a xyz position, or someone.\n\nThis plugin may works fine in the server MCDR supported.\n\n## Usage\nUse `!!etp <player_name>` to teleport to someone.\n\nUse `!!etp pos <x> <y> <z>` to teleport to a xyz-like position.\n\nUse `!!etp back` to teleport back with no refunds of ender pearls you cost.\n\n## Config\nServer owners set \"cost\" to a integer num in `config/ender_pearl_tp/config.json` to decide how many ender pearls players should cost to teleport where they want.\n\nDefault \"cost\" is 4.\n",
  "readme_url": "https://raw.githubusercontent.com/Mooling0602/Ender-Pearl-TP-MCDR/main/README.md",
  "license": {
    "key": "gpl-3.0",
    "name": "GNU General Public License v3.0",
    "spdx_id": "GPL-3.0",
    "url": "https://api.github.com/licenses/gpl-3.0"
  }
}