{
  "schema_version": 8,
  "id": "fbs_plugin",
  "latest_version": "1.1.1",
  "latest_version_index": 0,
  "releases": [
    {
      "url": "https://github.com/Walkersifolia/FastBotSpawn/releases/tag/1.1.1",
      "name": "v1.1.1",
      "tag_name": "1.1.1",
      "created_at": "2023-09-23T17:44:21Z",
      "description": "增加了自定义单次假人召唤上限的功能\r\n默认为10\r\n此功能即为上次添加的“限制单次生成的数量”",
      "prerelease": false,
      "asset": {
        "id": 127411538,
        "name": "FastBotSpawn-v1.1.1.mcdr",
        "size": 2576,
        "download_count": 86,
        "created_at": "2023-09-23T17:49:10Z",
        "browser_download_url": "https://github.com/Walkersifolia/FastBotSpawn/releases/download/1.1.1/FastBotSpawn-v1.1.1.mcdr",
        "hash_md5": "78c3a876ec9bb42507c4eacaf6981efe",
        "hash_sha256": "6b53deda8de0f4b210fb0f8acdc724ed56c68deeffea24d5462036362df77bc9"
      },
      "meta": {
        "schema_version": 4,
        "id": "fbs_plugin",
        "name": "FastBotSpawn",
        "version": "1.1.1",
        "link": "https://github.com/Walkersifolia/FastBotSpawn",
        "authors": [
          "WalkerTian"
        ],
        "dependencies": {},
        "requirements": [],
        "description": {
          "en_us": "A plugin with multiple functions"
        }
      }
    },
    {
      "url": "https://github.com/Walkersifolia/FastBotSpawn/releases/tag/1.1.0",
      "name": "v1.1.0",
      "tag_name": "1.1.0",
      "created_at": "2023-07-14T17:12:13Z",
      "description": "增加了自定义序号区间的功能\r\n限制单次生成的数量\r\n有想法欢迎提issue，我尽量实现",
      "prerelease": false,
      "asset": {
        "id": 117030689,
        "name": "FastBotSpawn-v1.1.0.mcdr",
        "size": 2543,
        "download_count": 45,
        "created_at": "2023-07-14T17:12:08Z",
        "browser_download_url": "https://github.com/Walkersifolia/FastBotSpawn/releases/download/1.1.0/FastBotSpawn-v1.1.0.mcdr",
        "hash_md5": "1c4fdd0d93b3aa9701dfe5a18bd6eb4c",
        "hash_sha256": "c284b086fdba21af1903f6532b6214f365d260aafbe2330781e940ee453915bc"
      },
      "meta": {
        "schema_version": 4,
        "id": "fbs_plugin",
        "name": "FastBotSpawn",
        "version": "1.1.0",
        "link": "https://github.com/Walkersifolia/FastBotSpawn",
        "authors": [
          "WalkerTian"
        ],
        "dependencies": {},
        "requirements": [],
        "description": {
          "en_us": "A plugin with multiple functions"
        }
      }
    }
  ]
}