{
  "schema_version": 4,
  "id": "prime_backup",
  "name": "Prime Backup",
  "version": "1.9.5",
  "link": "https://github.com/TISUnion/PrimeBackup",
  "authors": [
    "Fallen_Breath"
  ],
  "dependencies": {
    "mcdreforged": ">=2.12.0"
  },
  "requirements": [
    "APScheduler>=3.8,<4",
    "SQLAlchemy>=2",
    "mcdreforged>=2.12.0",
    "pathspec",
    "psutil",
    "pytz",
    "typing_extensions",
    "xxhash>=3",
    "zstandard"
  ],
  "description": {
    "en_us": "A powerful backup plugin for MCDR, an advanced backup solution for your Minecraft world",
    "zh_cn": "一个强大的MCDR备份插件，一套先进的Minecraft存档备份解决方案"
  }
}